{"catidnum":[{"item_url":"http://www.gayboystube.com/channels/12/Frat Guys/page1.html","thumb":"http://cdn.gayboystube.com/misc/cat12.jpg","catid":12,"items":[[{"path":"plugin://plugin.video.boyvid/play/2-4-2-1-5|24215565772aa84ded.mp4","label2":"426160","icon":"http://cdn.gayboystube.com/thumbs/2/4/2/1/5/24215565772aa84ded.mp4/24215565772aa84ded.mp4-2.jpg","thumbnail":"http://cdn.gayboystube.com/thumbs/2/4/2/1/5/24215565772aa84ded.mp4/24215565772aa84ded.mp4-2.jpg","label":"Greenhouse Effect ?"},{"path":"plugin://plugin.video.boyvid/play/2-4-2-1-5|242155657706452b0c.mp4","label2":"426159","icon":"http://cdn.gayboystube.com/thumbs/2/4/2/1/5/242155657706452b0c.mp4/242155657706452b0c.mp4-1.jpg","thumbnail":"http://cdn.gayboystube.com/thumbs/2/4/2/1/5/242155657706452b0c.mp4/242155657706452b0c.mp4-1.jpg","label":"Musing Of A Cute Solitary"},{"path":"plugin://plugin.video.boyvid/play/2-0-1-2-0|20120256576596a4a76.mp4","label2":"426154","icon":"http://cdn.gayboystube.com/thumbs/2/0/1/2/0/20120256576596a4a76.mp4/20120256576596a4a76.mp4-4.jpg","thumbnail":"http://cdn.gayboystube.com/thumbs/2/0/1/2/0/20120256576596a4a76.mp4/20120256576596a4a76.mp4-4.jpg","label":"Having Fun 13"},{"path":"plugin://plugin.video.boyvid/play/1-6-1-2-8|16128056572e4c5de09.mp4","label2":"426091","icon":"http://cdn.gayboystube.com/thumbs/1/6/1/2/8/16128056572e4c5de09.mp4/16128056572e4c5de09.mp4-2.jpg","thumbnail":"http://cdn.gayboystube.com/thumbs/1/6/1/2/8/16128056572e4c5de09.mp4/16128056572e4c5de09.mp4-2.jpg","label":"Nice Cock"},{"path":"plugin://plugin.video.boyvid/play/7-6-3-8-6|7638656572d729f7f6.flv","label2":"426090","icon":"http://cdn.gayboystube.com/thumbs/7/6/3/8/6/7638656572d729f7f6/7638656572d729f7f6.flv-1.jpg","thumbnail":"http://cdn.gayboystube.com/thumbs/7/6/3/8/6/7638656572d729f7f6/7638656572d729f7f6.flv-1.jpg","label":"Russian Guys Fuck"},{"path":"plugin://plugin.video.boyvid/play/6-5-7-3-2|6573256572fbae94a0.mp4","label2":"426100","icon":"http://cdn.gayboystube.com/thumbs/6/5/7/3/2/6573256572fbae94a0.mp4/6573256572fbae94a0.mp4-8.jpg","thumbnail":"http://cdn.gayboystube.com/thumbs/6/5/7/3/2/6573256572fbae94a0.mp4/6573256572fbae94a0.mp4-8.jpg","label":"Boys On Film"},{"path":"plugin://plugin.video.boyvid/play/1-0-0-0-0|1000025656fdf991a72.mp4","label2":"426099","icon":"http://cdn.gayboystube.com/thumbs/1/0/0/0/0/1000025656fdf991a72.mp4/1000025656fdf991a72.mp4-3.jpg","thumbnail":"http://cdn.gayboystube.com/thumbs/1/0/0/0/0/1000025656fdf991a72.mp4/1000025656fdf991a72.mp4-3.jpg","label":"Quickie B4 The Parents Are Home"},{"path":"plugin://plugin.video.boyvid/play/1-8-1-8-7|1818705657495db054e.mp4","label2":"426113","icon":"http://cdn.gayboystube.com/thumbs/1/8/1/8/7/1818705657495db054e.mp4/1818705657495db054e.mp4-3.jpg","thumbnail":"http://cdn.gayboystube.com/thumbs/1/8/1/8/7/1818705657495db054e.mp4/1818705657495db054e.mp4-3.jpg","label":"Better Than A Girlfriend"},{"path":"plugin://plugin.video.boyvid/play/2-0-0-8-2|20082056574e0a9c05f.mp4","label2":"426112","icon":"http://cdn.gayboystube.com/thumbs/2/0/0/8/2/20082056574e0a9c05f.mp4/20082056574e0a9c05f.mp4-8.jpg","thumbnail":"http://cdn.gayboystube.com/thumbs/2/0/0/8/2/20082056574e0a9c05f.mp4/20082056574e0a9c05f.mp4-8.jpg","label":"Red Hoodie Wank"},{"path":"plugin://plugin.video.boyvid/play/2-0-0-8-2|20082056574dbf6ae22.mp4","label2":"426111","icon":"http://cdn.gayboystube.com/thumbs/2/0/0/8/2/20082056574dbf6ae22.mp4/20082056574dbf6ae22.mp4-8.jpg","thumbnail":"http://cdn.gayboystube.com/thumbs/2/0/0/8/2/20082056574dbf6ae22.mp4/20082056574dbf6ae22.mp4-8.jpg","label":"Tub Wank "},{"path":"plugin://plugin.video.boyvid/play/1-6-1-2-8|1612805657524f149e4.flv","label2":"426117","icon":"http://cdn.gayboystube.com/thumbs/1/6/1/2/8/1612805657524f149e4/1612805657524f149e4.flv-4.jpg","thumbnail":"http://cdn.gayboystube.com/thumbs/1/6/1/2/8/1612805657524f149e4/1612805657524f149e4.flv-4.jpg","label":"With Sneakers"},{"path":"plugin://plugin.video.boyvid/play/1-6-1-2-8|161280565753d2df2a3.flv","label2":"426121","icon":"http://cdn.gayboystube.com/thumbs/1/6/1/2/8/161280565753d2df2a3/161280565753d2df2a3.flv-8.jpg","thumbnail":"http://cdn.gayboystube.com/thumbs/1/6/1/2/8/161280565753d2df2a3/161280565753d2df2a3.flv-8.jpg","label":"Bad Day For Go Visit"},{"path":"plugin://plugin.video.boyvid/play/1-6-1-2-8|16128056572b408df86.mp4","label2":"426089","icon":"http://cdn.gayboystube.com/thumbs/1/6/1/2/8/16128056572b408df86.mp4/16128056572b408df86.mp4-8.jpg","thumbnail":"http://cdn.gayboystube.com/thumbs/1/6/1/2/8/16128056572b408df86.mp4/16128056572b408df86.mp4-8.jpg","label":"Couple Who Want"},{"path":"plugin://plugin.video.boyvid/play/1-6-1-2-8|16128056572a2c2edb4.mp4","label2":"426086","icon":"http://cdn.gayboystube.com/thumbs/1/6/1/2/8/16128056572a2c2edb4.mp4/16128056572a2c2edb4.mp4-1.jpg","thumbnail":"http://cdn.gayboystube.com/thumbs/1/6/1/2/8/16128056572a2c2edb4.mp4/16128056572a2c2edb4.mp4-1.jpg","label":"Three Young Blond"},{"path":"plugin://plugin.video.boyvid/play/1-0-0-0-0|1000025656fc26bc361.mp4","label2":"426031","icon":"http://cdn.gayboystube.com/thumbs/1/0/0/0/0/1000025656fc26bc361.mp4/1000025656fc26bc361.mp4-7.jpg","thumbnail":"http://cdn.gayboystube.com/thumbs/1/0/0/0/0/1000025656fc26bc361.mp4/1000025656fc26bc361.mp4-7.jpg","label":"I Love My Dildo"},{"path":"plugin://plugin.video.boyvid/play/1-5-1-4-4|1514405657171c13e3a.mp4","label2":"426042","icon":"http://cdn.gayboystube.com/thumbs/1/5/1/4/4/1514405657171c13e3a.mp4/1514405657171c13e3a.mp4-7.jpg","thumbnail":"http://cdn.gayboystube.com/thumbs/1/5/1/4/4/1514405657171c13e3a.mp4/1514405657171c13e3a.mp4-7.jpg","label":"Watching Porn And Jerking."},{"path":"plugin://plugin.video.boyvid/play/3-9-5-1-3|395135657144073145.mp4","label2":"426041","icon":"http://cdn.gayboystube.com/thumbs/3/9/5/1/3/395135657144073145.mp4/395135657144073145.mp4-4.jpg","thumbnail":"http://cdn.gayboystube.com/thumbs/3/9/5/1/3/395135657144073145.mp4/395135657144073145.mp4-4.jpg","label":"Breaking In The New Car"},{"path":"plugin://plugin.video.boyvid/play/1-3-0-4-5|130454565710f4de063.mp4","label2":"426040","icon":"http://cdn.gayboystube.com/thumbs/1/3/0/4/5/130454565710f4de063.mp4/130454565710f4de063.mp4-8.jpg","thumbnail":"http://cdn.gayboystube.com/thumbs/1/3/0/4/5/130454565710f4de063.mp4/130454565710f4de063.mp4-8.jpg","label":"Up In The Barracks"},{"path":"plugin://plugin.video.boyvid/play/3-9-5-1-3|395135657164c5c6f5.mp4","label2":"426059","icon":"http://cdn.gayboystube.com/thumbs/3/9/5/1/3/395135657164c5c6f5.mp4/395135657164c5c6f5.mp4-8.jpg","thumbnail":"http://cdn.gayboystube.com/thumbs/3/9/5/1/3/395135657164c5c6f5.mp4/395135657164c5c6f5.mp4-8.jpg","label":"Prison Train Sex"},{"path":"plugin://plugin.video.boyvid/play/1-9-7-4-5|1974565657194341a2e.mp4","label2":"426064","icon":"http://cdn.gayboystube.com/thumbs/1/9/7/4/5/1974565657194341a2e.wmv/1974565657194341a2e.wmv-7.jpg","thumbnail":"http://cdn.gayboystube.com/thumbs/1/9/7/4/5/1974565657194341a2e.wmv/1974565657194341a2e.wmv-7.jpg","label":"Spunk Spunk Spunk!"},{"path":"plugin://plugin.video.boyvid/play/3-9-5-1-3|3951356571acec026c.mp4","label2":"426066","icon":"http://cdn.gayboystube.com/thumbs/3/9/5/1/3/3951356571acec026c.mp4/3951356571acec026c.mp4-4.jpg","thumbnail":"http://cdn.gayboystube.com/thumbs/3/9/5/1/3/3951356571acec026c.mp4/3951356571acec026c.mp4-4.jpg","label":"Guard Has Some Fun"},{"path":"plugin://plugin.video.boyvid/play/3-9-5-1-3|3951356571e591a203.mp4","label2":"426072","icon":"http://cdn.gayboystube.com/thumbs/3/9/5/1/3/3951356571e591a203.mp4/3951356571e591a203.mp4-7.jpg","thumbnail":"http://cdn.gayboystube.com/thumbs/3/9/5/1/3/3951356571e591a203.mp4/3951356571e591a203.mp4-7.jpg","label":"Special Prison Guard Attention"},{"path":"plugin://plugin.video.boyvid/play/8-5-2-8-7|8528756571f3c2e953.flv","label2":"426068","icon":"http://cdn.gayboystube.com/thumbs/8/5/2/8/7/8528756571f3c2e953/8528756571f3c2e953.flv-4.jpg","thumbnail":"http://cdn.gayboystube.com/thumbs/8/5/2/8/7/8528756571f3c2e953/8528756571f3c2e953.flv-4.jpg","label":"Hot Teens Layin Boys."},{"path":"plugin://plugin.video.boyvid/play/1-6-1-2-8|161280565720f9b8ffd.mp4","label2":"426071","icon":"http://cdn.gayboystube.com/thumbs/1/6/1/2/8/161280565720f9b8ffd.mp4/161280565720f9b8ffd.mp4-5.jpg","thumbnail":"http://cdn.gayboystube.com/thumbs/1/6/1/2/8/161280565720f9b8ffd.mp4/161280565720f9b8ffd.mp4-5.jpg","label":"Beautiful Young Masturbating"},{"path":"plugin://plugin.video.boyvid/play/1-6-1-2-8|16128056571f8a0a386.mp4","label2":"426069","icon":"http://cdn.gayboystube.com/thumbs/1/6/1/2/8/16128056571f8a0a386.mp4/16128056571f8a0a386.mp4-8.jpg","thumbnail":"http://cdn.gayboystube.com/thumbs/1/6/1/2/8/16128056571f8a0a386.mp4/16128056571f8a0a386.mp4-8.jpg","label":"Celebrating Thanksgiving Day"},{"path":"plugin://plugin.video.boyvid/play/1-6-1-2-8|1612805657223be2b18.mp4","label2":"426074","icon":"http://cdn.gayboystube.com/thumbs/1/6/1/2/8/1612805657223be2b18.mp4/1612805657223be2b18.mp4-8.jpg","thumbnail":"http://cdn.gayboystube.com/thumbs/1/6/1/2/8/1612805657223be2b18.mp4/1612805657223be2b18.mp4-8.jpg","label":"With Beautiful Blond Boy"},{"path":"plugin://plugin.video.boyvid/play/1-6-1-2-8|161280565728c37da25.mp4","label2":"426081","icon":"http://cdn.gayboystube.com/thumbs/1/6/1/2/8/161280565728c37da25.mp4/161280565728c37da25.mp4-1.jpg","thumbnail":"http://cdn.gayboystube.com/thumbs/1/6/1/2/8/161280565728c37da25.mp4/161280565728c37da25.mp4-1.jpg","label":"Beautiful Young In The Bathroom"},{"path":"plugin://plugin.video.boyvid/play/1-6-1-2-8|1612805657291fad079.mp4","label2":"426083","icon":"http://cdn.gayboystube.com/thumbs/1/6/1/2/8/1612805657291fad079.mp4/1612805657291fad079.mp4-8.jpg","thumbnail":"http://cdn.gayboystube.com/thumbs/1/6/1/2/8/1612805657291fad079.mp4/1612805657291fad079.mp4-8.jpg","label":"Caught While Masturbating"},{"path":"plugin://plugin.video.boyvid/play/1-6-1-2-8|16128056572aa94886c.mp4","label2":"426087","icon":"http://cdn.gayboystube.com/thumbs/1/6/1/2/8/16128056572aa94886c.mp4/16128056572aa94886c.mp4-4.jpg","thumbnail":"http://cdn.gayboystube.com/thumbs/1/6/1/2/8/16128056572aa94886c.mp4/16128056572aa94886c.mp4-4.jpg","label":"For Breakfast, Happiness"},{"path":"plugin://plugin.video.boyvid/play/1-3-0-4-5|1304545656f5d30549c.mp4","label2":"426027","icon":"http://cdn.gayboystube.com/thumbs/1/3/0/4/5/1304545656f5d30549c.mp4/1304545656f5d30549c.mp4-6.jpg","thumbnail":"http://cdn.gayboystube.com/thumbs/1/3/0/4/5/1304545656f5d30549c.mp4/1304545656f5d30549c.mp4-6.jpg","label":"Hotel Fun Time"},{"path":"plugin://plugin.video.boyvid/play/1-0-0-0-0|1000025656f9a7df6ae.mp4","label2":"426028","icon":"http://cdn.gayboystube.com/thumbs/1/0/0/0/0/1000025656f9a7df6ae.mp4/1000025656f9a7df6ae.mp4-3.jpg","thumbnail":"http://cdn.gayboystube.com/thumbs/1/0/0/0/0/1000025656f9a7df6ae.mp4/1000025656f9a7df6ae.mp4-3.jpg","label":"Fucking My Ass With A Dildo"},{"path":"plugin://plugin.video.boyvid/play/1-3-0-4-5|1304545656f8b3a0fc0.mp4","label2":"426029","icon":"http://cdn.gayboystube.com/thumbs/1/3/0/4/5/1304545656f8b3a0fc0.mp4/1304545656f8b3a0fc0.mp4-2.jpg","thumbnail":"http://cdn.gayboystube.com/thumbs/1/3/0/4/5/1304545656f8b3a0fc0.mp4/1304545656f8b3a0fc0.mp4-2.jpg","label":"Hot And Horny Sk8Rs"},{"path":"plugin://plugin.video.boyvid/play/1-3-0-4-5|1304545656fa65c9ef2.mp4","label2":"426032","icon":"http://cdn.gayboystube.com/thumbs/1/3/0/4/5/1304545656fa65c9ef2.mp4/1304545656fa65c9ef2.mp4-7.jpg","thumbnail":"http://cdn.gayboystube.com/thumbs/1/3/0/4/5/1304545656fa65c9ef2.mp4/1304545656fa65c9ef2.mp4-7.jpg","label":"Making Love"},{"path":"plugin://plugin.video.boyvid/play/1-3-0-4-5|13045456570daa5ae71.mp4","label2":"426038","icon":"http://cdn.gayboystube.com/thumbs/1/3/0/4/5/13045456570daa5ae71.mp4/13045456570daa5ae71.mp4-2.jpg","thumbnail":"http://cdn.gayboystube.com/thumbs/1/3/0/4/5/13045456570daa5ae71.mp4/13045456570daa5ae71.mp4-2.jpg","label":"Let'S Go To The Pool"},{"path":"plugin://plugin.video.boyvid/play/1-3-0-4-5|13045456570a4c637a5.mp4","label2":"426037","icon":"http://cdn.gayboystube.com/thumbs/1/3/0/4/5/13045456570a4c637a5.mp4/13045456570a4c637a5.mp4-2.jpg","thumbnail":"http://cdn.gayboystube.com/thumbs/1/3/0/4/5/13045456570a4c637a5.mp4/13045456570a4c637a5.mp4-2.jpg","label":"Waiting To Interview"},{"path":"plugin://plugin.video.boyvid/play/1-3-0-4-5|130454565704bbe4faf.mp4","label2":"426036","icon":"http://cdn.gayboystube.com/thumbs/1/3/0/4/5/130454565704bbe4faf.mp4/130454565704bbe4faf.mp4-1.jpg","thumbnail":"http://cdn.gayboystube.com/thumbs/1/3/0/4/5/130454565704bbe4faf.mp4/130454565704bbe4faf.mp4-1.jpg","label":"Welcoming The New Guy Onto The Team"},{"path":"plugin://plugin.video.boyvid/play/2-0-5-9-9|2059955657084a588da.mp4","label2":"426034","icon":"http://cdn.gayboystube.com/thumbs/2/0/5/9/9/2059955657084a588da.mp4/2059955657084a588da.mp4-6.jpg","thumbnail":"http://cdn.gayboystube.com/thumbs/2/0/5/9/9/2059955657084a588da.mp4/2059955657084a588da.mp4-6.jpg","label":"Cute Aussie Cums All Over His Face"},{"path":"plugin://plugin.video.boyvid/play/1-7-5-3-4|175346565708e2701d0.mp4","label2":"426035","icon":"http://cdn.gayboystube.com/thumbs/1/7/5/3/4/175346565708e2701d0.mp4/175346565708e2701d0.mp4-1.jpg","thumbnail":"http://cdn.gayboystube.com/thumbs/1/7/5/3/4/175346565708e2701d0.mp4/175346565708e2701d0.mp4-1.jpg","label":"Ggbt Having A Quick Pull"},{"path":"plugin://plugin.video.boyvid/play/1-3-0-4-5|1304545656fee3a15e2.mp4","label2":"426033","icon":"http://cdn.gayboystube.com/thumbs/1/3/0/4/5/1304545656fee3a15e2.mp4/1304545656fee3a15e2.mp4-4.jpg","thumbnail":"http://cdn.gayboystube.com/thumbs/1/3/0/4/5/1304545656fee3a15e2.mp4/1304545656fee3a15e2.mp4-4.jpg","label":"Gym Friend"},{"path":"plugin://plugin.video.boyvid/play/1-8-1-8-7|1818705656e32e30b2b.mp4","label2":"426026","icon":"http://cdn.gayboystube.com/thumbs/1/8/1/8/7/1818705656e32e30b2b.mp4/1818705656e32e30b2b.mp4-8.jpg","thumbnail":"http://cdn.gayboystube.com/thumbs/1/8/1/8/7/1818705656e32e30b2b.mp4/1818705656e32e30b2b.mp4-8.jpg","label":"Bedroom Scallies"}]],"filename":"cat-12.json","catname":"Frat Guys","catnamesafe":"Frat Guys","path":"plugin://plugin.video.boyvid/cat/12/Frat Guys/p/1","icon":"http://cdn.gayboystube.com/misc/cat12.jpg"},1448572813.382181]}